keep_sabbath/__init__.py
keep_sabbath/admin.py
keep_sabbath/apps.py
keep_sabbath/models.py
keep_sabbath/sabbath.py
keep_sabbath/tests.py
keep_sabbath/urls.py
keep_sabbath/views.py
keep_sabbath/vendor/solartime.py
keep_sabbath-0.7.0.dist-info/LICENSE
keep_sabbath-0.7.0.dist-info/METADATA
keep_sabbath-0.7.0.dist-info/WHEEL
keep_sabbath-0.7.0.dist-info/top_level.txt
keep_sabbath-0.7.0.dist-info/RECORD
