Metadata-Version: 2.1
Name: keep-sabbath
Version: 0.7.0
Summary: Django app to automatically redirect users when it is the Sabbath day, with support for overriding on other Biblical Holy days.
Home-page: https://github.com/Correct-Syntax/Keep-Sabbath/
Author: Noah Rahm
Author-email: hi@noahrahm.com
License: BSD 3-Clause
Keywords: sabbath,django,web,redirects
Classifier: Development Status :: 4 - Beta
Classifier: Intended Audience :: Developers
Classifier: Operating System :: OS Independent
Classifier: Environment :: Web Environment
Classifier: Framework :: Django
Classifier: Topic :: Software Development :: Build Tools
Classifier: License :: OSI Approved :: BSD License
Classifier: Programming Language :: Python :: 3
Classifier: Programming Language :: Python :: 3.9
Classifier: Programming Language :: Python :: 3.10
Classifier: Programming Language :: Python :: 3.11
License-File: LICENSE
Requires-Dist: django (>=3.2)
